L9110_I2C.py
mke_m17_v2-0.1.1.dist-info/licenses/LICENSE
mke_m17_v2-0.1.1.dist-info/METADATA
mke_m17_v2-0.1.1.dist-info/WHEEL
mke_m17_v2-0.1.1.dist-info/top_level.txt
mke_m17_v2-0.1.1.dist-info/RECORD
