Metadata-Version: 2.4
Name: mke-m17-v2
Version: 0.1.1
Summary: A Python/MicroPython driver for the L9110 motor controller over I2C
Author-email: Quy-An <quyan18b@gmail.com>
Project-URL: Homepage, https://github.com/Quy-An/MKE-M17-V2
Project-URL: Documentation, https://github.com/Quy-An/MKE-M17-V2/blob/main/README.md
Classifier: Programming Language :: Python :: 3
Classifier: Programming Language :: Python :: Implementation :: MicroPython
Classifier: License :: OSI Approved :: MIT License
Classifier: Operating System :: OS Independent
Classifier: Topic :: Software Development :: Embedded Systems
Requires-Python: >=3.6
License-File: LICENSE
Requires-Dist: smbus2>=0.4.3; platform_system != "MicroPython"
Dynamic: license-file
